hr_tddschn/__init__.py
hr_tddschn/hr.py
hr_tddschn/utils.py
hr_tddschn-0.1.9.dist-info/entry_points.txt
hr_tddschn-0.1.9.dist-info/LICENSE
hr_tddschn-0.1.9.dist-info/WHEEL
hr_tddschn-0.1.9.dist-info/METADATA
hr_tddschn-0.1.9.dist-info/RECORD
